{
  "id": "d0f94aae-330a-4923-b10d-d215c0c7be94",
  "prevId": "71c62068-cf62-465c-b18b-5fe7c0875a3f",
  "version": "5",
  "dialect": "pg",
  "tables": {
    "addresses": {
      "name": "addresses",
      "schema": "",
      "columns": {
        "id": {
          "name": "id",
          "type": "serial",
          "primaryKey": true,
          "notNull": true
        },
        "addressLine1": {
          "name": "addressLine1",
          "type": "text",
          "primaryKey": false,
          "notNull": true
        },
        "addressLine2": {
          "name": "addressLine2",
          "type": "text",
          "primaryKey": false,
          "notNull": false
        },
        "city": {
          "name": "city",
          "type": "text",
          "primaryKey": false,
          "notNull": true
        },
        "district": {
          "name": "district",
          "type": "text",
          "primaryKey": false,
          "notNull": true
        },
        "state": {
          "name": "state",
          "type": "text",
          "primaryKey": false,
          "notNull": true
        },
        "pinCode": {
          "name": "pinCode",
          "type": "varchar(12)",
          "primaryKey": false,
          "notNull": true
        },
        "createdAt": {
          "name": "createdAt",
          "type": "timestamp",
          "primaryKey": false,
          "notNull": false,
          "default": "now()"
        }
      },
      "indexes": {},
      "foreignKeys": {},
      "compositePrimaryKeys": {},
      "uniqueConstraints": {}
    },
    "bankDetails": {
      "name": "bankDetails",
      "schema": "",
      "columns": {
        "id": {
          "name": "id",
          "type": "serial",
          "primaryKey": true,
          "notNull": true
        },
        "accountNumber": {
          "name": "accountNumber",
          "type": "text",
          "primaryKey": false,
          "notNull": true
        },
        "ifsc": {
          "name": "ifsc",
          "type": "text",
          "primaryKey": false,
          "notNull": true
        },
        "branch": {
          "name": "branch",
          "type": "text",
          "primaryKey": false,
          "notNull": true
        },
        "createdAt": {
          "name": "createdAt",
          "type": "timestamp",
          "primaryKey": false,
          "notNull": true,
          "default": "now()"
        }
      },
      "indexes": {},
      "foreignKeys": {},
      "compositePrimaryKeys": {},
      "uniqueConstraints": {}
    },
    "categories": {
      "name": "categories",
      "schema": "",
      "columns": {
        "id": {
          "name": "id",
          "type": "serial",
          "primaryKey": true,
          "notNull": true
        },
        "name": {
          "name": "name",
          "type": "varchar(256)",
          "primaryKey": false,
          "notNull": true
        },
        "createdAt": {
          "name": "createdAt",
          "type": "timestamp",
          "primaryKey": false,
          "notNull": true,
          "default": "now()"
        }
      },
      "indexes": {},
      "foreignKeys": {},
      "compositePrimaryKeys": {},
      "uniqueConstraints": {}
    },
    "departments": {
      "name": "departments",
      "schema": "",
      "columns": {
        "id": {
          "name": "id",
          "type": "serial",
          "primaryKey": true,
          "notNull": true
        },
        "name": {
          "name": "name",
          "type": "varchar(256)",
          "primaryKey": false,
          "notNull": true
        },
        "createdAt": {
          "name": "createdAt",
          "type": "timestamp",
          "primaryKey": false,
          "notNull": true,
          "default": "now()"
        }
      },
      "indexes": {},
      "foreignKeys": {},
      "compositePrimaryKeys": {},
      "uniqueConstraints": {
        "departments_name_unique": {
          "name": "departments_name_unique",
          "nullsNotDistinct": false,
          "columns": [
            "name"
          ]
        }
      }
    },
    "fabrics": {
      "name": "fabrics",
      "schema": "",
      "columns": {
        "id": {
          "name": "id",
          "type": "serial",
          "primaryKey": true,
          "notNull": true
        },
        "grade": {
          "name": "grade",
          "type": "text",
          "primaryKey": false,
          "notNull": true
        },
        "createdAt": {
          "name": "createdAt",
          "type": "timestamp",
          "primaryKey": false,
          "notNull": true,
          "default": "now()"
        }
      },
      "indexes": {},
      "foreignKeys": {},
      "compositePrimaryKeys": {},
      "uniqueConstraints": {
        "fabrics_grade_unique": {
          "name": "fabrics_grade_unique",
          "nullsNotDistinct": false,
          "columns": [
            "grade"
          ]
        }
      }
    },
    "tableList": {
      "name": "tableList",
      "schema": "",
      "columns": {
        "id": {
          "name": "id",
          "type": "serial",
          "primaryKey": true,
          "notNull": true
        },
        "categoryId": {
          "name": "categoryId",
          "type": "integer",
          "primaryKey": false,
          "notNull": true
        },
        "name": {
          "name": "name",
          "type": "text",
          "primaryKey": false,
          "notNull": true
        },
        "minQuantity": {
          "name": "minQuantity",
          "type": "integer",
          "primaryKey": false,
          "notNull": true
        },
        "unit": {
          "name": "unit",
          "type": "varchar(256)",
          "primaryKey": false,
          "notNull": true
        },
        "createdAt": {
          "name": "createdAt",
          "type": "timestamp",
          "primaryKey": false,
          "notNull": true,
          "default": "now()"
        }
      },
      "indexes": {},
      "foreignKeys": {
        "tableList_categoryId_categories_id_fk": {
          "name": "tableList_categoryId_categories_id_fk",
          "tableFrom": "tableList",
          "tableTo": "categories",
          "columnsFrom": [
            "categoryId"
          ],
          "columnsTo": [
            "id"
          ],
          "onDelete": "no action",
          "onUpdate": "no action"
        }
      },
      "compositePrimaryKeys": {},
      "uniqueConstraints": {
        "tableList_name_unique": {
          "name": "tableList_name_unique",
          "nullsNotDistinct": false,
          "columns": [
            "name"
          ]
        }
      }
    },
    "users": {
      "name": "users",
      "schema": "",
      "columns": {
        "id": {
          "name": "id",
          "type": "serial",
          "primaryKey": true,
          "notNull": true
        },
        "firstName": {
          "name": "firstName",
          "type": "varchar(256)",
          "primaryKey": false,
          "notNull": true
        },
        "lastName": {
          "name": "lastName",
          "type": "varchar(256)",
          "primaryKey": false,
          "notNull": true
        },
        "role": {
          "name": "role",
          "type": "integer",
          "primaryKey": false,
          "notNull": true
        },
        "email": {
          "name": "email",
          "type": "text",
          "primaryKey": false,
          "notNull": true
        },
        "createdAt": {
          "name": "createdAt",
          "type": "timestamp",
          "primaryKey": false,
          "notNull": true,
          "default": "now()"
        },
        "clerkId": {
          "name": "clerkId",
          "type": "text",
          "primaryKey": false,
          "notNull": true
        }
      },
      "indexes": {},
      "foreignKeys": {},
      "compositePrimaryKeys": {},
      "uniqueConstraints": {
        "users_email_unique": {
          "name": "users_email_unique",
          "nullsNotDistinct": false,
          "columns": [
            "email"
          ]
        }
      }
    },
    "vendors": {
      "name": "vendors",
      "schema": "",
      "columns": {
        "id": {
          "name": "id",
          "type": "serial",
          "primaryKey": true,
          "notNull": true
        },
        "type": {
          "name": "type",
          "type": "integer",
          "primaryKey": false,
          "notNull": true,
          "default": 0
        },
        "name": {
          "name": "name",
          "type": "text",
          "primaryKey": false,
          "notNull": true
        },
        "contactNumber": {
          "name": "contactNumber",
          "type": "varchar(12)",
          "primaryKey": false,
          "notNull": true
        },
        "emailId": {
          "name": "emailId",
          "type": "text",
          "primaryKey": false,
          "notNull": true
        },
        "categoryId": {
          "name": "categoryId",
          "type": "integer",
          "primaryKey": false,
          "notNull": true
        },
        "addressId": {
          "name": "addressId",
          "type": "integer",
          "primaryKey": false,
          "notNull": true
        },
        "bankDetailsId": {
          "name": "bankDetailsId",
          "type": "integer",
          "primaryKey": false,
          "notNull": true
        },
        "createdAt": {
          "name": "createdAt",
          "type": "timestamp",
          "primaryKey": false,
          "notNull": false,
          "default": "now()"
        },
        "gstNumber": {
          "name": "gstNumber",
          "type": "text",
          "primaryKey": false,
          "notNull": true
        },
        "pan": {
          "name": "pan",
          "type": "varchar(10)",
          "primaryKey": false,
          "notNull": true
        }
      },
      "indexes": {
        "name": {
          "name": "name",
          "columns": [
            "name"
          ],
          "isUnique": false
        }
      },
      "foreignKeys": {
        "vendors_categoryId_categories_id_fk": {
          "name": "vendors_categoryId_categories_id_fk",
          "tableFrom": "vendors",
          "tableTo": "categories",
          "columnsFrom": [
            "categoryId"
          ],
          "columnsTo": [
            "id"
          ],
          "onDelete": "no action",
          "onUpdate": "no action"
        },
        "vendors_addressId_addresses_id_fk": {
          "name": "vendors_addressId_addresses_id_fk",
          "tableFrom": "vendors",
          "tableTo": "addresses",
          "columnsFrom": [
            "addressId"
          ],
          "columnsTo": [
            "id"
          ],
          "onDelete": "no action",
          "onUpdate": "no action"
        },
        "vendors_bankDetailsId_bankDetails_id_fk": {
          "name": "vendors_bankDetailsId_bankDetails_id_fk",
          "tableFrom": "vendors",
          "tableTo": "bankDetails",
          "columnsFrom": [
            "bankDetailsId"
          ],
          "columnsTo": [
            "id"
          ],
          "onDelete": "no action",
          "onUpdate": "no action"
        }
      },
      "compositePrimaryKeys": {},
      "uniqueConstraints": {
        "vendors_emailId_unique": {
          "name": "vendors_emailId_unique",
          "nullsNotDistinct": false,
          "columns": [
            "emailId"
          ]
        },
        "vendors_gstNumber_unique": {
          "name": "vendors_gstNumber_unique",
          "nullsNotDistinct": false,
          "columns": [
            "gstNumber"
          ]
        }
      }
    }
  },
  "enums": {},
  "schemas": {},
  "_meta": {
    "columns": {},
    "schemas": {},
    "tables": {}
  }
}